KaliLinuxDoc/README.md
KaliLinuxDoc/__init__.py
KaliLinuxDoc/__main__.py
KaliLinuxDoc/file.epub
KaliLinuxDoc/index.html
KaliLinuxDoc/css/__init__.py
KaliLinuxDoc/css/annotations.css
KaliLinuxDoc/css/main.css
KaliLinuxDoc/css/normalize.css
KaliLinuxDoc/css/popup.css
KaliLinuxDoc/font/__init__.py
KaliLinuxDoc/font/fontello.eot
KaliLinuxDoc/font/fontello.svg
KaliLinuxDoc/font/fontello.ttf
KaliLinuxDoc/font/fontello.woff
KaliLinuxDoc/img/__init__.py
KaliLinuxDoc/img/annotator-glyph-sprite.png
KaliLinuxDoc/img/annotator-icon-sprite.png
KaliLinuxDoc/img/apple-touch-icon.png
KaliLinuxDoc/img/cancelfullscreen.png
KaliLinuxDoc/img/close.png
KaliLinuxDoc/img/fullscreen.png
KaliLinuxDoc/img/loader.gif
KaliLinuxDoc/img/menu-icon.png
KaliLinuxDoc/img/save.png
KaliLinuxDoc/img/saved.png
KaliLinuxDoc/img/settings-s.png
KaliLinuxDoc/img/settings.png
KaliLinuxDoc/img/star.png
KaliLinuxDoc/js/__init__.py
KaliLinuxDoc/js/epub.js
KaliLinuxDoc/js/epub.min.js
KaliLinuxDoc/js/epub.min.map
KaliLinuxDoc/js/hooks.min.js
KaliLinuxDoc/js/hooks.min.map
KaliLinuxDoc/js/reader.js
KaliLinuxDoc/js/reader.js.map
KaliLinuxDoc/js/reader.min.js
KaliLinuxDoc/js/reader.min.map
KaliLinuxDoc/js/hooks/__init__.py
KaliLinuxDoc/js/hooks/extensions/__init__.py
KaliLinuxDoc/js/hooks/extensions/highlight.js
KaliLinuxDoc/js/libs/__init__.py
KaliLinuxDoc/js/libs/jquery.min.js
KaliLinuxDoc/js/libs/localforage.min.js
KaliLinuxDoc/js/libs/screenfull.js
KaliLinuxDoc/js/libs/screenfull.min.js
KaliLinuxDoc/js/libs/zip.min.js
KaliLinuxDoc/js/plugins/__init__.py
KaliLinuxDoc/js/plugins/hypothesis.js
KaliLinuxDoc/js/plugins/search.js
kali_linux_doc-2024.3.1.0.dist-info/METADATA
kali_linux_doc-2024.3.1.0.dist-info/WHEEL
kali_linux_doc-2024.3.1.0.dist-info/entry_points.txt
kali_linux_doc-2024.3.1.0.dist-info/top_level.txt
kali_linux_doc-2024.3.1.0.dist-info/RECORD
